setup.py
gb_distribution_package/Binomialdistribution.py
gb_distribution_package/Gaussiandistribution.py
gb_distribution_package/Generaldistribution.py
gb_distribution_package/__init__.py
gb_distribution_package.egg-info/PKG-INFO
gb_distribution_package.egg-info/SOURCES.txt
gb_distribution_package.egg-info/dependency_links.txt
gb_distribution_package.egg-info/not-zip-safe
gb_distribution_package.egg-info/top_level.txt