Metadata-Version: 1.0
Name: gb-distribution-package
Version: 0.1
Summary: Gaussian distributions
Home-page: UNKNOWN
Author: Prashant Kumar
Author-email: mail2pk1105@gmail.com
License: UNKNOWN
Platform: UNKNOWN
